etu_django_mcmt/__init__.py
etu_django_mcmt/admin.py
etu_django_mcmt/apps.py
etu_django_mcmt/models.py
etu_django_mcmt/tests.py
etu_django_mcmt/views.py
etu_django_mcmt/core/__init__.py
etu_django_mcmt/core/ver_222/__init__.py
etu_django_mcmt/core/ver_222/makemigrations.py
etu_django_mcmt/core/ver_222/migrate.py
etu_django_mcmt/core/ver_3213/__init__.py
etu_django_mcmt/core/ver_3213/makemigrations.py
etu_django_mcmt/core/ver_3213/migrate.py
etu_django_mcmt/docs/DOCS.md
etu_django_mcmt/management/__init__.py
etu_django_mcmt/management/commands/__init__.py
etu_django_mcmt/management/commands/db_makemigrations.py
etu_django_mcmt/management/commands/db_migrate.py
etu_django_mcmt/migrations/__init__.py
etu_django_mcmt/utils/__init__.py
etu_django_mcmt/utils/commapi.py
etu_django_mcmt/utils/db_cache_api.py
etu_django_mcmt-1.0.2.dist-info/LICENSE
etu_django_mcmt-1.0.2.dist-info/METADATA
etu_django_mcmt-1.0.2.dist-info/WHEEL
etu_django_mcmt-1.0.2.dist-info/top_level.txt
etu_django_mcmt-1.0.2.dist-info/zip-safe
etu_django_mcmt-1.0.2.dist-info/RECORD
