Metadata-Version: 2.1
Name: etu-django-mcmt
Version: 1.0.2
Summary: Etu Django Migrations Cache Manager Tool。
Author: Jieay
Author-email: 1016900854@qq.com
License: Apache License
Classifier: Intended Audience :: Developers
Classifier: License :: OSI Approved :: Apache Software License
Classifier: Programming Language :: Python
Classifier: Programming Language :: Python :: 3
Classifier: Programming Language :: Python :: 3.6
Classifier: Programming Language :: Python :: 3.7
Classifier: Programming Language :: Python :: 3.8
Classifier: Programming Language :: Python :: 3.9
Classifier: Topic :: Software Development :: Libraries
License-File: LICENSE
Requires-Dist: Django (>=2.2)
